tokenize2/__init__.py
tokenize2/tokenizer.py
tokenize2/utils.py
Tokenize2-2.0.3.dist-info/METADATA
Tokenize2-2.0.3.dist-info/WHEEL
Tokenize2-2.0.3.dist-info/top_level.txt
Tokenize2-2.0.3.dist-info/RECORD
