Metadata-Version: 2.1
Name: Tokenize2
Version: 2.0.3
Summary: A byte-level BPE tokenizer for efficient text processing
Home-page: https://github.com/TnsaAi/Tokenize2
Author: TNSA AI
Author-email: thishyakethabimalla@gmail.com
License: MIT
Classifier: Programming Language :: Python :: 3
Classifier: License :: OSI Approved :: MIT License
Classifier: Operating System :: OS Independent
Requires-Python: >=3.6
